{
  "introduction": {
    "workbook": "01",
    "prereqs": [],
    "x": -25.964896415633888,
    "y": -53.67131536738474
  },
  "matter_energy_intro": {
    "workbook": "01",
    "prereqs": [],
    "x": -22.186035827103822,
    "y": -30.9271895533193
  },
  "conservation_mass_energy": {
    "workbook": "01",
    "prereqs": [
      "matter_energy_intro"
    ],
    "x": -43.579407929317014,
    "y": -16.78599936926919
  },
  "mass_weight_gravity": {
    "workbook": "01",
    "prereqs": [],
    "x": -19.45720353300633,
    "y": 62.59090879773248
  },
  "intro_motion": {
    "workbook": "01",
    "prereqs": [],
    "x": 34.1904095270246,
    "y": 68.19030235541783
  },
  "newtons_second_law": {
    "workbook": "01",
    "prereqs": [
      "mass_weight_gravity"
    ],
    "x": 7.607147652069727,
    "y": 40.61306930213145
  },
  "friction": {
    "workbook": "01",
    "prereqs": [
      "conservation_mass_energy",
      "newtons_second_law"
    ],
    "x": -10.613037744615696,
    "y": -57.11230584634369
  },
  "units_conversions": {
    "workbook": "01",
    "prereqs": [],
    "x": 59.13950760002351,
    "y": -37.44865622052286
  },
  "greek": {
    "workbook": "01",
    "prereqs": [],
    "x": 45.410870896580036,
    "y": 33.73295034617355
  },
  "atomic_mass": {
    "workbook": "02",
    "prereqs": [
      "matter_energy_intro"
    ],
    "x": 40.99238592782953,
    "y": 67.67208505289796
  },
  "chemical_reactions": {
    "workbook": "02",
    "prereqs": [
      "matter_energy_intro"
    ],
    "x": 64.57634391556383,
    "y": 9.524191339063663
  },
  "buoyancy": {
    "workbook": "02",
    "prereqs": [],
    "x": -47.15958901851475,
    "y": 39.91632985759564
  },
  "heat": {
    "workbook": "02",
    "prereqs": [
      "conservation_mass_energy"
    ],
    "x": -18.26426562603647,
    "y": 12.067925988078997
  },
  "work_energy": {
    "workbook": "02",
    "prereqs": [
      "matter_energy_intro",
      "newtons_second_law"
    ],
    "x": -51.77782692061416,
    "y": -1.7623692342668846
  },
  "simple_machines": {
    "workbook": "02",
    "prereqs": [
      "work_energy"
    ],
    "x": -24.223309586930476,
    "y": 59.53632601403288
  },
  "basic_statistics": {
    "workbook": "03",
    "prereqs": [],
    "x": 22.527609811904327,
    "y": 22.238035750273227
  },
  "stat_spreadsheets": {
    "workbook": "03",
    "prereqs": [
      "basic_statistics"
    ],
    "x": 5.051783398174194,
    "y": -16.814323952790794
  },
  "intro_python1": {
    "workbook": "03",
    "prereqs": [],
    "x": 68.23198553816084,
    "y": -28.074682740416876
  },
  "sets": {
    "workbook": "03",
    "prereqs": [],
    "x": -62.46846017711343,
    "y": -61.13026670350283
  },
  "proofs": {
    "workbook": "03",
    "prereqs": [
      "sets"
    ],
    "x": 65.06811204758651,
    "y": -24.945840280284685
  },
  "dc1": {
    "workbook": "03",
    "prereqs": [
      "basic_statistics",
      "greek",
      "units_conversions",
      "work_energy"
    ],
    "x": -66.63889222248667,
    "y": 48.22951838835347
  },
  "dc_circuits": {
    "workbook": "03",
    "prereqs": [
      "dc1",
      "work_energy"
    ],
    "x": 50.75146588026924,
    "y": 59.76404323652076
  },
  "fertilizer": {
    "workbook": "04",
    "prereqs": [
      "matter_energy_intro"
    ],
    "x": 66.99158673188617,
    "y": 63.362974182860455
  },
  "concrete": {
    "workbook": "04",
    "prereqs": [
      "matter_energy_intro"
    ],
    "x": -52.873492836750884,
    "y": -67.3325598657885
  },
  "metals": {
    "workbook": "04",
    "prereqs": [
      "atomic_mass",
      "matter_energy_intro",
      "work_energy"
    ],
    "x": 14.614423161000076,
    "y": 56.83773615181299
  },
  "intro_python2": {
    "workbook": "04",
    "prereqs": [
      "intro_python1",
      "proofs"
    ],
    "x": 14.287119491717348,
    "y": -55.70740708674828
  },
  "angles": {
    "workbook": "04",
    "prereqs": [],
    "x": -5.3980426017049865,
    "y": -1.9009896457182975
  },
  "triangles": {
    "workbook": "04",
    "prereqs": [
      "angles"
    ],
    "x": -36.5362535984661,
    "y": -51.93820504347936
  },
  "pythagorean_theorem": {
    "workbook": "04",
    "prereqs": [
      "triangles"
    ],
    "x": -9.535177937899562,
    "y": -57.174046510838565
  },
  "congruence": {
    "workbook": "05",
    "prereqs": [
      "angles",
      "triangles"
    ],
    "x": -59.43460298406734,
    "y": 34.360073988204846
  },
  "parallel_perpendicular": {
    "workbook": "05",
    "prereqs": [
      "angles",
      "pythagorean_theorem"
    ],
    "x": 26.55708183475214,
    "y": 61.03514485016831
  },
  "circles": {
    "workbook": "05",
    "prereqs": [
      "angles"
    ],
    "x": -26.179098979463454,
    "y": 43.51954965808157
  },
  "functions": {
    "workbook": "05",
    "prereqs": [
      "congruence"
    ],
    "x": 37.53606321523591,
    "y": -29.745865771387173
  },
  "transforms": {
    "workbook": "05",
    "prereqs": [
      "congruence",
      "functions"
    ],
    "x": -21.11125192102758,
    "y": 19.432360622767433
  },
  "trig_functions": {
    "workbook": "06",
    "prereqs": [
      "angles",
      "functions",
      "pythagorean_theorem"
    ],
    "x": -52.65795278424927,
    "y": -49.74983998237569
  },
  "trig_identities": {
    "workbook": "06",
    "prereqs": [
      "pythagorean_theorem",
      "triangles",
      "trig_functions"
    ],
    "x": 0.3577586418263792,
    "y": 59.63209509330326
  },
  "volume_solids": {
    "workbook": "06",
    "prereqs": [],
    "x": 12.543716925120123,
    "y": 59.53381170078785
  },
  "conic_sections": {
    "workbook": "06",
    "prereqs": [
      "volume_solids"
    ],
    "x": 34.75672147371182,
    "y": 40.48652015365978
  },
  "vectors": {
    "workbook": "06",
    "prereqs": [
      "angles",
      "intro_python2",
      "parallel_perpendicular",
      "pythagorean_theorem"
    ],
    "x": 22.32690612288107,
    "y": 57.40368243518904
  },
  "falling_bodies": {
    "workbook": "07",
    "prereqs": [
      "conic_sections",
      "intro_python1",
      "matter_energy_intro",
      "newtons_second_law"
    ],
    "x": -59.798871233367734,
    "y": -19.567750069199505
  },
  "kinematics": {
    "workbook": "07",
    "prereqs": [
      "falling_bodies",
      "newtons_second_law"
    ],
    "x": -42.891198656732925,
    "y": -3.010925846125815
  },
  "projectiles": {
    "workbook": "07",
    "prereqs": [
      "angles",
      "kinematics",
      "mass_weight_gravity",
      "trig_functions"
    ],
    "x": 68.26373691743808,
    "y": -39.57021938937991
  },
  "free_body_diagrams": {
    "workbook": "07",
    "prereqs": [
      "conservation_mass_energy",
      "newtons_second_law",
      "vectors"
    ],
    "x": -57.08604537713992,
    "y": 63.739119492124985
  },
  "inclines": {
    "workbook": "07",
    "prereqs": [
      "angles",
      "free_body_diagrams",
      "friction",
      "newtons_second_law",
      "simple_machines",
      "triangles",
      "trig_functions"
    ],
    "x": 8.260587503024155,
    "y": 54.414238407791544
  },
  "momentum": {
    "workbook": "07",
    "prereqs": [
      "conservation_mass_energy",
      "mass_weight_gravity",
      "vectors",
      "work_energy"
    ],
    "x": -15.250633936719318,
    "y": -43.241692628672865
  },
  "boats": {
    "workbook": "08",
    "prereqs": [
      "buoyancy",
      "matter_energy_intro",
      "newtons_second_law"
    ],
    "x": 53.6225806454527,
    "y": -60.688414264280354
  },
  "sailing": {
    "workbook": "08",
    "prereqs": [
      "boats"
    ],
    "x": 28.212882128607234,
    "y": 21.92440969136844
  },
  "airplanes": {
    "workbook": "08",
    "prereqs": [
      "boats",
      "falling_bodies",
      "newtons_second_law",
      "sailing",
      "vectors"
    ],
    "x": 51.77700063373568,
    "y": 50.4673497972758
  },
  "pandas": {
    "workbook": "08",
    "prereqs": [
      "intro_python2"
    ],
    "x": -59.796339740420265,
    "y": -50.27774119660087
  },
  "quadcopters": {
    "workbook": "08",
    "prereqs": [],
    "x": 68.19797944241787,
    "y": -56.79891640960821
  },
  "helicopters": {
    "workbook": "08",
    "prereqs": [],
    "x": 49.7129213085135,
    "y": -33.533439378797745
  },
  "atmopressure": {
    "workbook": "09",
    "prereqs": [
      "buoyancy",
      "matter_energy_intro",
      "newtons_second_law",
      "work_energy"
    ],
    "x": -65.59682632263497,
    "y": -1.954825477046512
  },
  "biases1": {
    "workbook": "09",
    "prereqs": [],
    "x": -42.191872704375754,
    "y": -18.92246049287734
  },
  "solving_quadratics": {
    "workbook": "09",
    "prereqs": [
      "conic_sections"
    ],
    "x": 24.677817953854614,
    "y": 20.873903538631254
  },
  "complex_numbers": {
    "workbook": "09",
    "prereqs": [
      "solving_quadratics"
    ],
    "x": -22.819288026550957,
    "y": 24.061476865811258
  },
  "sequences": {
    "workbook": "09",
    "prereqs": [],
    "x": 39.316122130621636,
    "y": -21.32347959909906
  },
  "exponents_review": {
    "workbook": "10",
    "prereqs": [
      "functions"
    ],
    "x": 31.957827374738358,
    "y": -9.030783457419169
  },
  "compound_interest": {
    "workbook": "10",
    "prereqs": [
      "exponents_review",
      "stat_spreadsheets"
    ],
    "x": 36.79075795846788,
    "y": -21.14908663142549
  },
  "logs": {
    "workbook": "10",
    "prereqs": [
      "exponents_review",
      "intro_python2",
      "stat_spreadsheets"
    ],
    "x": -28.675987341878503,
    "y": -43.89386296038687
  },
  "exponential_decay": {
    "workbook": "10",
    "prereqs": [
      "compound_interest",
      "exponents_review",
      "stat_spreadsheets"
    ],
    "x": 9.85463610979528,
    "y": 55.764436464449304
  },
  "inv_trig_functions": {
    "workbook": "10",
    "prereqs": [
      "functions",
      "pythagorean_theorem",
      "trig_functions"
    ],
    "x": -3.3775142211095073,
    "y": -12.922335471658961
  },
  "graphs": {
    "workbook": "10",
    "prereqs": [
      "intro_dataviz",
      "intro_python2"
    ],
    "x": -55.304626629418905,
    "y": 2.9376124879504744
  },
  "paradoxes": {
    "workbook": "10",
    "prereqs": [
      "intro_python2",
      "pandas",
      "proofs",
      "sets"
    ],
    "x": 36.078149636528224,
    "y": -31.650468709085267
  },
  "intro_dataviz": {
    "workbook": "11",
    "prereqs": [
      "compound_interest",
      "functions",
      "stat_spreadsheets"
    ],
    "x": -14.033491234945288,
    "y": 65.72533390814834
  },
  "num_methods": {
    "workbook": "11",
    "prereqs": [],
    "x": 11.595397068321475,
    "y": 51.97444968328193
  },
  "dot": {
    "workbook": "11",
    "prereqs": [
      "inv_trig_functions",
      "parallel_perpendicular",
      "trig_functions",
      "vectors"
    ],
    "x": 0.8262658032294325,
    "y": 52.19743705636256
  },
  "manufacturing": {
    "workbook": "11",
    "prereqs": [
      "metals"
    ],
    "x": -4.046393528733759,
    "y": 12.388679282878968
  },
  "intro_waves": {
    "workbook": "11",
    "prereqs": [
      "parallel_perpendicular",
      "trig_functions"
    ],
    "x": -40.34931215664669,
    "y": 53.33329170038709
  },
  "sound": {
    "workbook": "11",
    "prereqs": [
      "matter_energy_intro",
      "trig_functions"
    ],
    "x": -19.21650904971073,
    "y": -24.43267909109222
  },
  "num_methods_2": {
    "workbook": "11",
    "prereqs": [
      "num_methods"
    ],
    "x": -17.409922383000477,
    "y": 39.73507067918035
  },
  "charge": {
    "workbook": "12",
    "prereqs": [
      "conservation_mass_energy",
      "dc1",
      "exponents_review",
      "greek",
      "mass_weight_gravity",
      "matter_energy_intro",
      "newtons_second_law",
      "vectors",
      "work_energy"
    ],
    "x": -37.997214425468364,
    "y": 55.6774722877079
  },
  "ac": {
    "workbook": "12",
    "prereqs": [
      "basic_statistics",
      "dc1",
      "trig_functions"
    ],
    "x": 31.83483281837296,
    "y": 66.25193106012574
  },
  "induction": {
    "workbook": "12",
    "prereqs": [
      "ac",
      "charge"
    ],
    "x": -26.865328960438553,
    "y": 20.449974811670742
  },
  "electric_motors_generators": {
    "workbook": "12",
    "prereqs": [
      "induction"
    ],
    "x": -32.622419372981504,
    "y": -67.25871528456736
  },
  "drag": {
    "workbook": "12",
    "prereqs": [
      "airplanes",
      "falling_bodies",
      "free_body_diagrams",
      "newtons_second_law",
      "projectiles",
      "trig_functions"
    ],
    "x": -36.96829244868644,
    "y": -1.6106519434925843
  },
  "parametric": {
    "workbook": "12",
    "prereqs": [
      "differentiating_polynomials",
      "functions",
      "intro_python2",
      "solving_quadratics",
      "trig_identities"
    ],
    "x": -62.783401567959636,
    "y": 61.17329730614691
  },
  "vector_functions": {
    "workbook": "12",
    "prereqs": [
      "differentiating_polynomials",
      "drag",
      "parametric",
      "vectors"
    ],
    "x": -13.09523062799731,
    "y": 23.248561049670187
  },
  "circular": {
    "workbook": "12",
    "prereqs": [
      "circles",
      "conservation_mass_energy",
      "projectiles"
    ],
    "x": 4.666685349310555,
    "y": -68.78212437255306
  },
  "emwaves": {
    "workbook": "13",
    "prereqs": [
      "sound"
    ],
    "x": -14.683747248041946,
    "y": 0.05459732720653676
  },
  "reflection": {
    "workbook": "13",
    "prereqs": [
      "conic_sections",
      "emwaves",
      "pythagorean_theorem",
      "work_energy"
    ],
    "x": 28.098311082099556,
    "y": 44.84509243460802
  },
  "refraction": {
    "workbook": "13",
    "prereqs": [
      "reflection"
    ],
    "x": 55.97460640459144,
    "y": 46.115486832826846
  },
  "lens": {
    "workbook": "13",
    "prereqs": [
      "reflection",
      "refraction"
    ],
    "x": 59.951914424894426,
    "y": -33.67871899252957
  },
  "oscillations": {
    "workbook": "13",
    "prereqs": [
      "basic_statistics",
      "differentiating_polynomials",
      "parametric",
      "trig_functions",
      "work_energy"
    ],
    "x": -46.21506211766939,
    "y": 43.94484218575214
  },
  "orbits": {
    "workbook": "13",
    "prereqs": [
      "circular",
      "falling_bodies",
      "mass_weight_gravity",
      "reflection"
    ],
    "x": 7.205766331604465,
    "y": -24.96841456344457
  },
  "polar_coord": {
    "workbook": "13",
    "prereqs": [
      "angles",
      "circular",
      "functions",
      "inv_trig_functions",
      "parametric",
      "trig_identities"
    ],
    "x": -54.418624615135066,
    "y": 67.19023059171982
  },
  "circular_2": {
    "workbook": "14",
    "prereqs": [
      "angles",
      "circles",
      "circular",
      "cross"
    ],
    "x": -2.2391578106535377,
    "y": 0.8932609730708094
  },
  "rocketry": {
    "workbook": "14",
    "prereqs": [
      "airplanes",
      "newtons_second_law",
      "orbits"
    ],
    "x": -58.08136214012892,
    "y": 24.454678880810903
  },
  "vector_sim": {
    "workbook": "14",
    "prereqs": [
      "intro_python2",
      "mass_weight_gravity",
      "momentum",
      "orbits",
      "vectors"
    ],
    "x": 6.667347570512391,
    "y": 48.079892964126
  },
  "long_lat_dist": {
    "workbook": "14",
    "prereqs": [],
    "x": 61.87876044421131,
    "y": -37.13146137697924
  },
  "tides": {
    "workbook": "14",
    "prereqs": [
      "circular",
      "orbits"
    ],
    "x": 15.031521255422476,
    "y": -54.913159895984464
  },
  "sampling": {
    "workbook": "14",
    "prereqs": [],
    "x": 34.92925825337767,
    "y": 6.741286871995996
  },
  "camera": {
    "workbook": "15",
    "prereqs": [
      "emwaves",
      "lens",
      "reflection"
    ],
    "x": 25.323451119037955,
    "y": 68.79932892655256
  },
  "eye": {
    "workbook": "15",
    "prereqs": [
      "camera",
      "reflection"
    ],
    "x": -59.885011020525404,
    "y": 0.9909558811522032
  },
  "py_images": {
    "workbook": "15",
    "prereqs": [
      "camera"
    ],
    "x": 17.55828157923517,
    "y": 49.678909689471624
  },
  "hexbinary": {
    "workbook": "15",
    "prereqs": [
      "camera"
    ],
    "x": -5.359112273929767,
    "y": 53.037434890652946
  },
  "bitmap": {
    "workbook": "15",
    "prereqs": [
      "hexbinary"
    ],
    "x": 28.72168454557722,
    "y": -68.78799830466154
  },
  "floating": {
    "workbook": "15",
    "prereqs": [],
    "x": 3.087898659695014,
    "y": 25.661917652993097
  },
  "polynomials_intro": {
    "workbook": "16",
    "prereqs": [
      "functions"
    ],
    "x": 1.8420548736006168,
    "y": 58.12601666578743
  },
  "pylists": {
    "workbook": "16",
    "prereqs": [
      "polynomials_intro"
    ],
    "x": 29.548042425661578,
    "y": -58.12143016819225
  },
  "add_subtract_polynomials": {
    "workbook": "16",
    "prereqs": [
      "polynomials_intro",
      "pylists"
    ],
    "x": -30.906637940446394,
    "y": -41.84512433632219
  },
  "multiplying_polynomials": {
    "workbook": "16",
    "prereqs": [
      "polynomials_intro"
    ],
    "x": -34.71227487815675,
    "y": 8.032135143708075
  },
  "pymultpoly": {
    "workbook": "16",
    "prereqs": [
      "multiplying_polynomials"
    ],
    "x": 51.970085497297376,
    "y": -59.17136850244384
  },
  "differentiating_polynomials": {
    "workbook": "17",
    "prereqs": [
      "add_subtract_polynomials",
      "polynomials_intro"
    ],
    "x": -69.61747570233915,
    "y": -45.546782611502096
  },
  "classes": {
    "workbook": "17",
    "prereqs": [
      "differentiating_polynomials"
    ],
    "x": -58.34407441956646,
    "y": -63.50057430242143
  },
  "common_products_polynomials": {
    "workbook": "17",
    "prereqs": [
      "multiplying_polynomials",
      "polynomials_intro"
    ],
    "x": -43.10443916846506,
    "y": 40.66342048913333
  },
  "factoring_polynomials": {
    "workbook": "17",
    "prereqs": [
      "common_products_polynomials"
    ],
    "x": 62.92455605944372,
    "y": -4.485255648472986
  },
  "practice_polynomials": {
    "workbook": "17",
    "prereqs": [
      "common_products_polynomials",
      "factoring_polynomials",
      "multiplying_polynomials",
      "polynomials_intro",
      "solving_quadratics"
    ],
    "x": 29.865247720666503,
    "y": 54.09406554594629
  },
  "graphs_polynomials": {
    "workbook": "18",
    "prereqs": [
      "factoring_polynomials",
      "multiplying_polynomials",
      "polynomials_intro"
    ],
    "x": 63.095006171599266,
    "y": 35.67449216628256
  },
  "interpolating_polynomials": {
    "workbook": "18",
    "prereqs": [
      "factoring_polynomials",
      "polynomials_intro"
    ],
    "x": -24.668327601849356,
    "y": -63.85178647221775
  },
  "rational_functions": {
    "workbook": "18",
    "prereqs": [
      "functions"
    ],
    "x": -43.62574637664517,
    "y": 42.64139651612054
  },
  "partial_frac": {
    "workbook": "18",
    "prereqs": [
      "polynomials_intro",
      "rational_functions"
    ],
    "x": -51.276198241718106,
    "y": 0.20877930444262915
  },
  "limits": {
    "workbook": "18",
    "prereqs": [
      "basic_statistics",
      "functions",
      "rational_functions"
    ],
    "x": -51.34597048837189,
    "y": 57.9067313206769
  },
  "differentiability": {
    "workbook": "19",
    "prereqs": [
      "limits"
    ],
    "x": 4.37721350594515,
    "y": 31.986258143674334
  },
  "derivative_definition": {
    "workbook": "19",
    "prereqs": [
      "differentiability",
      "differentiating_polynomials",
      "limits"
    ],
    "x": 34.00549210133252,
    "y": -47.647703862967404
  },
  "derivative_rules": {
    "workbook": "19",
    "prereqs": [
      "differentiability",
      "differentiating_polynomials"
    ],
    "x": 4.536468963838701,
    "y": 36.64091151110608
  },
  "deriv_graphshape": {
    "workbook": "19",
    "prereqs": [
      "differentiating_polynomials",
      "graphs_polynomials"
    ],
    "x": 69.0387929981813,
    "y": 54.62996940219459
  },
  "optimization": {
    "workbook": "20",
    "prereqs": [],
    "x": -63.08241290565779,
    "y": 63.3518325633045
  },
  "implicit_diff": {
    "workbook": "20",
    "prereqs": [
      "derivative_rules",
      "differentiability"
    ],
    "x": -67.60670856567332,
    "y": 42.67269315303372
  },
  "related_rates": {
    "workbook": "20",
    "prereqs": [
      "differentiability",
      "implicit_diff"
    ],
    "x": -63.61712685704374,
    "y": -28.450634884872116
  },
  "multiv_func": {
    "workbook": "20",
    "prereqs": [
      "differentiability",
      "differentiating_polynomials"
    ],
    "x": -35.779263374273484,
    "y": -31.11628477740139
  },
  "partial_deriv_grad": {
    "workbook": "20",
    "prereqs": [
      "derivative_rules",
      "dot",
      "multiv_func"
    ],
    "x": 38.00366036844275,
    "y": -64.49258414123499
  },
  "linear_algebra_intro": {
    "workbook": "21",
    "prereqs": [
      "camera",
      "dot",
      "py_images",
      "vector_functions",
      "vectors"
    ],
    "x": -11.455506860866649,
    "y": -51.420780306102756
  },
  "vectors_matrices": {
    "workbook": "21",
    "prereqs": [
      "bitmap",
      "dot",
      "linear_algebra_intro",
      "vectors"
    ],
    "x": -19.285091467556406,
    "y": -65.62458925615167
  },
  "linear_combo": {
    "workbook": "21",
    "prereqs": [
      "linear_algebra_intro"
    ],
    "x": -36.25836082684794,
    "y": -56.138242463917685
  },
  "systems_matrices": {
    "workbook": "21",
    "prereqs": [
      "vectors_matrices"
    ],
    "x": 5.897420085114561,
    "y": 11.013950641410275
  },
  "matrices_applications": {
    "workbook": "21",
    "prereqs": [
      "dot",
      "linear_combo",
      "vectors_matrices"
    ],
    "x": -36.51969728736775,
    "y": -55.575111689695234
  },
  "dependence": {
    "workbook": "21",
    "prereqs": [
      "linear_combo",
      "matrices_applications",
      "systems_matrices",
      "vectors",
      "vectors_matrices"
    ],
    "x": 47.99544134361382,
    "y": -38.15801299539036
  },
  "subspaces": {
    "workbook": "21",
    "prereqs": [
      "dependence",
      "systems_matrices"
    ],
    "x": 23.89247781688141,
    "y": 10.870785712005386
  },
  "span": {
    "workbook": "22",
    "prereqs": [
      "dependence",
      "linear_combo",
      "subspaces"
    ],
    "x": -60.337582938400644,
    "y": 62.27592449440175
  },
  "determinants_inverse": {
    "workbook": "22",
    "prereqs": [
      "dependence",
      "linear_combo",
      "systems_matrices"
    ],
    "x": 47.43432965997093,
    "y": -58.72860221018399
  },
  "cross": {
    "workbook": "22",
    "prereqs": [
      "determinants_inverse",
      "dot",
      "span"
    ],
    "x": -23.16612267101501,
    "y": -66.6107098214948
  },
  "transformations": {
    "workbook": "22",
    "prereqs": [
      "bitmap",
      "congruence",
      "determinants_inverse",
      "vectors_matrices"
    ],
    "x": 29.189854169161634,
    "y": -62.9831953537175
  },
  "eigen": {
    "workbook": "22",
    "prereqs": [
      "determinants_inverse",
      "dot",
      "linear_combo",
      "transformations",
      "vectors"
    ],
    "x": 9.953959611820139,
    "y": 52.79548996136447
  },
  "projections": {
    "workbook": "22",
    "prereqs": [
      "dot",
      "vectors"
    ],
    "x": 16.365889242836744,
    "y": -56.86411481633199
  },
  "gram-schmidt": {
    "workbook": "23",
    "prereqs": [
      "projections",
      "vectors"
    ],
    "x": -39.91077431896437,
    "y": 36.00652689777502
  },
  "decomposition": {
    "workbook": "23",
    "prereqs": [
      "eigen"
    ],
    "x": -11.464295426690242,
    "y": -34.52387985355647
  },
  "positive-semidefinite": {
    "workbook": "23",
    "prereqs": [
      "vectors_matrices"
    ],
    "x": 4.489495407576385,
    "y": -31.895723786678367
  },
  "intro_c": {
    "workbook": "23",
    "prereqs": [
      "intro_python2"
    ],
    "x": 0.3118901161802796,
    "y": -21.806843697252305
  },
  "sql_1": {
    "workbook": "24",
    "prereqs": [],
    "x": 18.835916908838044,
    "y": 3.6822887168354583
  },
  "diodes": {
    "workbook": "24",
    "prereqs": [],
    "x": 12.12100445183495,
    "y": 69.21446595841556
  },
  "trees": {
    "workbook": "24",
    "prereqs": [
      "graphs",
      "intro_python2",
      "proofs"
    ],
    "x": 39.83418519146174,
    "y": -51.491894209795014
  },
  "tree_traversal": {
    "workbook": "24",
    "prereqs": [
      "intro_python2",
      "trees"
    ],
    "x": -66.9543257211205,
    "y": -61.74266274932915
  },
  "shortest_path": {
    "workbook": "24",
    "prereqs": [
      "graphs",
      "tree_traversal"
    ],
    "x": -2.8689286289970113,
    "y": 31.625996948886467
  },
  "priority_queues": {
    "workbook": "24",
    "prereqs": [],
    "x": 48.36905869745566,
    "y": 12.123122794006349
  },
  "graph_algorithms": {
    "workbook": "24",
    "prereqs": [
      "graphs",
      "intro_python2",
      "proofs",
      "sets",
      "shortest_path",
      "tree_traversal"
    ],
    "x": -5.169472398180403,
    "y": 18.540673186386883
  },
  "http": {
    "workbook": "25",
    "prereqs": [],
    "x": 42.392558122986884,
    "y": -0.17827477267807978
  },
  "api": {
    "workbook": "25",
    "prereqs": [
      "http"
    ],
    "x": -54.692126443816534,
    "y": 66.9468036303943
  },
  "decompression": {
    "workbook": "25",
    "prereqs": [],
    "x": 65.9854180144587,
    "y": 64.95596332652767
  },
  "json_xml": {
    "workbook": "25",
    "prereqs": [],
    "x": 52.773579897723494,
    "y": -7.474861125551357
  },
  "html": {
    "workbook": "26",
    "prereqs": [
      "http"
    ],
    "x": 46.18971460297233,
    "y": 36.553382916306276
  },
  "intro_text": {
    "workbook": "26",
    "prereqs": [
      "hexbinary"
    ],
    "x": -17.040084561728186,
    "y": 46.83059579518664
  },
  "stop_words": {
    "workbook": "26",
    "prereqs": [],
    "x": -10.56282021590286,
    "y": 19.387755166844954
  },
  "accents_scripts": {
    "workbook": "27",
    "prereqs": [
      "greek",
      "intro_text"
    ],
    "x": -19.206845331977974,
    "y": 56.7925739086417
  },
  "matplotlib": {
    "workbook": "27",
    "prereqs": [],
    "x": -15.962499168756601,
    "y": 2.6330254210298136
  },
  "geocoding": {
    "workbook": "27",
    "prereqs": [
      "api",
      "http",
      "json_xml",
      "long_lat_dist"
    ],
    "x": 18.576331166696136,
    "y": -61.588254274802225
  },
  "making_a_map": {
    "workbook": "28",
    "prereqs": [
      "intro_python2",
      "long_lat_dist"
    ],
    "x": 5.018898780099192,
    "y": -23.50387239788288
  },
  "discrete_probability": {
    "workbook": "28",
    "prereqs": [
      "basic_statistics",
      "functions",
      "pylists"
    ],
    "x": 61.510115091711356,
    "y": -49.329821536249725
  },
  "combinatorics": {
    "workbook": "28",
    "prereqs": [
      "common_products_polynomials",
      "discrete_probability",
      "exponents_review",
      "polynomials_intro"
    ],
    "x": 9.066601285650663,
    "y": -61.89111199716251
  },
  "permutations": {
    "workbook": "28",
    "prereqs": [
      "combinatorics",
      "functions",
      "intro_python2",
      "vectors_matrices"
    ],
    "x": 12.182835221645476,
    "y": -20.1756435668522
  },
  "conditional_prob": {
    "workbook": "29",
    "prereqs": [
      "discrete_probability"
    ],
    "x": 6.350310714714823,
    "y": -1.6444599848913697
  },
  "bayes": {
    "workbook": "29",
    "prereqs": [
      "conditional_prob"
    ],
    "x": 56.57143971282245,
    "y": 10.907618540545684
  },
  "intro_markov": {
    "workbook": "29",
    "prereqs": [
      "conditional_prob",
      "discrete_probability",
      "eigen",
      "graphs",
      "limits",
      "matrices_applications",
      "vectors_matrices"
    ],
    "x": -32.0095104823364,
    "y": 51.34097249118666
  },
  "antiderivatives": {
    "workbook": "29",
    "prereqs": [
      "differentiating_polynomials"
    ],
    "x": 9.281925167410577,
    "y": 46.583967519872175
  },
  "riemann_sums": {
    "workbook": "29",
    "prereqs": [
      "antiderivatives",
      "intro_python2"
    ],
    "x": -21.789922044835798,
    "y": 3.046714139941855
  },
  "stemming_lemmatization": {
    "workbook": "29",
    "prereqs": [
      "intro_markov"
    ],
    "x": 53.294578488990794,
    "y": 7.779563723297983
  },
  "definite_integral": {
    "workbook": "30",
    "prereqs": [
      "antiderivatives",
      "riemann_sums"
    ],
    "x": 43.874293222542676,
    "y": 53.758760302681935
  },
  "ftc": {
    "workbook": "30",
    "prereqs": [],
    "x": -13.471945071019483,
    "y": -47.7414713315012
  },
  "arc_length": {
    "workbook": "30",
    "prereqs": [
      "definite_integral",
      "pythagorean_theorem"
    ],
    "x": 13.606641967044268,
    "y": 18.42794247455666
  },
  "cdf_uniform": {
    "workbook": "30",
    "prereqs": [
      "bayes",
      "conditional_prob",
      "definite_integral",
      "discrete_probability"
    ],
    "x": -1.6907426513247827,
    "y": 68.46808976861959
  },
  "gas": {
    "workbook": "31",
    "prereqs": [
      "atmopressure",
      "atomic_mass",
      "basic_statistics",
      "cdf_uniform",
      "matter_energy_intro",
      "newtons_second_law",
      "work_energy"
    ],
    "x": -34.290288417555345,
    "y": -20.885011438952958
  },
  "temp_kinetic": {
    "workbook": "31",
    "prereqs": [
      "gas"
    ],
    "x": -58.69318171937034,
    "y": 5.114149411860211
  },
  "phase_change": {
    "workbook": "31",
    "prereqs": [
      "temp_kinetic"
    ],
    "x": 64.1634852395305,
    "y": -46.92774382535841
  },
  "engine": {
    "workbook": "31",
    "prereqs": [
      "gas",
      "rocketry"
    ],
    "x": 10.86651712290302,
    "y": 9.330506928935833
  },
  "u-substitution": {
    "workbook": "32",
    "prereqs": [
      "antiderivatives",
      "definite_integral",
      "differentiability"
    ],
    "x": -66.79980444960628,
    "y": 48.088097235477136
  },
  "polar_calc": {
    "workbook": "32",
    "prereqs": [
      "circular",
      "inv_trig_functions",
      "parametric",
      "polar_coord",
      "trig_identities"
    ],
    "x": -0.08627369649127559,
    "y": -3.2159882650123137
  },
  "diff_eqs": {
    "workbook": "32",
    "prereqs": [
      "compound_interest",
      "partial_deriv_grad"
    ],
    "x": 5.903925741787177,
    "y": -3.1599127218141803
  },
  "slope_fields": {
    "workbook": "32",
    "prereqs": [
      "diff_eqs"
    ],
    "x": -2.8239517975838595,
    "y": 40.353952364158545
  },
  "euler_method": {
    "workbook": "33",
    "prereqs": [
      "diff_eqs"
    ],
    "x": 5.29334644516166,
    "y": 31.03346939571597
  },
  "seq_calc": {
    "workbook": "33",
    "prereqs": [
      "compound_interest",
      "derivative_definition",
      "intro_python2",
      "limits",
      "sequences"
    ],
    "x": 17.946562935969595,
    "y": -57.478321848395055
  },
  "series": {
    "workbook": "33",
    "prereqs": [
      "seq_calc",
      "sequences"
    ],
    "x": 31.194348031261327,
    "y": -62.81555948486573
  },
  "series_tests": {
    "workbook": "33",
    "prereqs": [
      "seq_calc",
      "series"
    ],
    "x": 45.62849915677687,
    "y": -24.476375877906435
  },
  "power_series": {
    "workbook": "34",
    "prereqs": [
      "series",
      "series_tests"
    ],
    "x": -13.37990368038755,
    "y": 55.500588277156254
  },
  "pop_prop": {
    "workbook": "34",
    "prereqs": [
      "bayes",
      "combinatorics",
      "conditional_prob"
    ],
    "x": -58.528737221188265,
    "y": -14.441216285682763
  },
  "normal_t": {
    "workbook": "34",
    "prereqs": [
      "basic_statistics",
      "cdf_uniform"
    ],
    "x": -42.74196026339654,
    "y": -15.534339949829935
  },
  "change_var": {
    "workbook": "34",
    "prereqs": [
      "basic_statistics",
      "cdf_uniform"
    ],
    "x": -17.52007885865931,
    "y": -26.771738074456728
  },
  "volume_single_integral": {
    "workbook": "34",
    "prereqs": [
      "definite_integral",
      "volume_solids"
    ],
    "x": 16.0457978789197,
    "y": -64.81655483241043
  },
  "volume_double_integral": {
    "workbook": "35",
    "prereqs": [
      "definite_integral",
      "multiv_func",
      "volume_single_integral"
    ],
    "x": 29.821408346334096,
    "y": 48.726762595484686
  },
  "double_int_regions": {
    "workbook": "35",
    "prereqs": [
      "volume_double_integral"
    ],
    "x": 47.731858765086514,
    "y": -44.8175546606316
  },
  "double_int_applications": {
    "workbook": "35",
    "prereqs": [
      "double_int_regions"
    ],
    "x": -63.45932645169644,
    "y": -19.044844121238015
  },
  "multiv_dist": {
    "workbook": "35",
    "prereqs": [
      "multiv_func"
    ],
    "x": -6.762743423977483,
    "y": 54.95411858540969
  },
  "multiv_normal": {
    "workbook": "36",
    "prereqs": [
      "normal_t"
    ],
    "x": 63.90981316882983,
    "y": 41.997096683426335
  },
  "numerical_multi_int": {
    "workbook": "36",
    "prereqs": [
      "double_int_regions",
      "multiv_func",
      "riemann_sums"
    ],
    "x": 9.244895856936026,
    "y": 28.359761505408542
  },
  "bayes_classifier": {
    "workbook": "36",
    "prereqs": [
      "bayes",
      "conditional_prob",
      "multiv_normal"
    ],
    "x": -46.23216229730481,
    "y": -11.64200768513794
  }
}