[
  {
    "requires": [
      "projections",
      "unit_vector"
    ],
    "title": "The Gram-Schmidt Process",
    "id": "gram-schmidt",
    "chap_num": 1,
    "covers": [
      {
        "id": "gram-schmidt",
        "desc": "Understand how to use the gram-schmidt process for vectors",
        "videos": [
          {
            "link": "https://www.youtube.com/watch?v=pIy8xqh9sWs",
            "title": "Gram-Schmidt Process in Space (Step-by-Step 3D Visual) - YouTube"
          },
          {
            "link": "https://www.youtube.com/watch?v=KOkuTXrv5Gg",
            "title": "Gram-Schmidt Orthogonalization - YouTube"
          },
          {
            "link": "https://www.youtube.com/watch?v=xW31FZuiwAM",
            "title": "Gram-Schmidt Orthogonalization (Proof and Example) | Linear Algebra - YouTube"
          },
          {
            "link": "https://youtu.be/zHbfZWZJTGc",
            "title": "The Gram-Schmidt Process - YouTube"
          },
          {
            "link": "https://youtu.be/zti01DiImiQ",
            "title": "Full example: using Gram-Schmidt - YouTube"
          },
          {
            "link": "https://www.youtube.com/watch?v=rHonltF77zI",
            "title": "The Gram-Schmidt process | Alternate coordinate systems (bases) | Linear Algebra | Khan Academy - YouTube"
          }
        ],
        "references": [
          {
            "link": "https://www.geeksforgeeks.org/machine-learning/gram-schmidt-process-for-ml/",
            "title": "Gram Schmidt Process for ML - GeeksforGeeks"
          },
          {
            "link": "https://en.wikipedia.org/wiki/Gram%E2%80%93Schmidt_process",
            "title": "Gram\u2013Schmidt process - Wikipedia"
          },
          {
            "link": "https://en.wikipedia.org/wiki/Orthogonal_basis",
            "title": "Orthogonal basis - Wikipedia"
          }
        ]
      }
    ],
    "start_page": 3
  },
  {
    "requires": [
      "eigen"
    ],
    "title": "Singular Value Decomposition",
    "id": "decomposition",
    "chap_num": 2,
    "covers": [
      {
        "id": "svd",
        "desc": "Understand how to use SVD in both in mathematics and python. ",
        "videos": [
          {
            "link": "https://youtu.be/vSczTbgc8Rc",
            "title": "SVD Visualized, Singular Value Decomposition explained | SEE Matrix , Chapter 3 #SoME2 - YouTube"
          },
          {
            "link": "https://youtu.be/mBcLRGuAFUk",
            "title": "Singular Value Decomposition (the SVD) - YouTube"
          },
          {
            "link": "https://youtu.be/CpD9XlTu3ys",
            "title": "What is the Singular Value Decomposition? - YouTube"
          }
        ],
        "references": [
          {
            "link": "https://www.ams.org/publicoutreach/feature-column/fcarc-svd",
            "title": "AMS :: Feature Column from the AMS"
          }
        ]
      }
    ],
    "start_page": 9
  },
  {
    "requires": [
      "matrix_oper",
      "matrix"
    ],
    "title": "Tackling Difficult Problems: Positive Semidefinite Matrices",
    "id": "positive-semidefinite",
    "chap_num": 3,
    "covers": [
      {
        "id": "positive-semidefinite",
        "desc": "Understand how to calculate positive semidefinite values",
        "videos": [
          {
            "link": "https://youtu.be/xsP-S7yKaRA",
            "title": "5. Positive Definite and Semidefinite Matrices - YouTube"
          },
          {
            "link": "https://youtu.be/2uKoKKLgZ4c",
            "title": "What Does It Mean For a Matrix to be POSITIVE? The Practical Guide to  Semidefinite Programming(1/4) - YouTube"
          },
          {
            "link": "https://youtu.be/UCc9q_cAhho",
            "title": "25. Symmetric Matrices and Positive Definiteness - YouTube"
          },
          {
            "link": "https://youtu.be/lpnY5QVjU5w",
            "title": "Symmetric Matrices and Positive Definiteness - YouTube"
          }
        ],
        "references": [
          {
            "link": "https://en.wikipedia.org/wiki/Positive_semidefinite",
            "title": "Positive semidefinite - Wikipedia"
          }
        ]
      }
    ],
    "start_page": 17
  }
]